conf2levels/__init__.py
conf2levels/argparse_reader.py
conf2levels/dictonary_reader.py
conf2levels/environ_reader.py
conf2levels/exceptions.py
conf2levels/ini_reader.py
conf2levels/py.typed
conf2levels/reader_base.py
conf2levels/spec_reader.py
conf2levels/types.py
conf2levels-0.5.1.dist-info/LICENSE
conf2levels-0.5.1.dist-info/METADATA
conf2levels-0.5.1.dist-info/WHEEL
conf2levels-0.5.1.dist-info/RECORD
