Metadata-Version: 2.1
Name: conf2levels
Version: 0.5.1
Summary: A configuration reader which reads values stored in two key levels. The first key level is named “section” and the second level “key”.
License: MIT
Author: Josef Friedrich
Author-email: josef@friedrich.rocks
Requires-Python: >=3.10,<4.0
Classifier: License :: OSI Approved :: MIT License
Classifier: Programming Language :: Python :: 3
Classifier: Programming Language :: Python :: 3.10
Classifier: Programming Language :: Python :: 3.11
Classifier: Programming Language :: Python :: 3.12
Classifier: Programming Language :: Python :: 3 :: Only
Classifier: Topic :: Utilities
Requires-Dist: typing-extensions (>=4.3.0,<5.0.0)
